smartbytes/__init__.py
smartbytes/smartbytes.py
smartbytes-1.5.4.dist-info/LICENSE.md
smartbytes-1.5.4.dist-info/METADATA
smartbytes-1.5.4.dist-info/WHEEL
smartbytes-1.5.4.dist-info/top_level.txt
smartbytes-1.5.4.dist-info/RECORD
