Metadata-Version: 2.1
Name: smartbytes
Version: 1.5.4
Summary: makes bytes in Python significantly less painful
Home-page: https://github.com/Arinerron/smartbytes
Author: Aaron Esau
Author-email: python@aaronesau.com
License: UNKNOWN
Keywords: smartbytes bytes str string bytesarray byte parsing pwntools pwn ctf
Platform: UNKNOWN
